pyqoi/__init__.py
pyqoi/pyqoi.py
pyqoi_lib-0.1.0.dist-info/LICENSE
pyqoi_lib-0.1.0.dist-info/METADATA
pyqoi_lib-0.1.0.dist-info/WHEEL
pyqoi_lib-0.1.0.dist-info/top_level.txt
pyqoi_lib-0.1.0.dist-info/RECORD
