Metadata-Version: 2.2
Name: pyqoi-lib
Version: 0.1.0
Summary: A Python implementation of the QOI (Quite OK Image) format
Home-page: https://github.com/prakashsellathurai/pyqoi
Author: Prakash S
Author-email: prakashsellathurai@gmail.com
Classifier: Programming Language :: Python :: 3
Classifier: License :: OSI Approved :: MIT License
Classifier: Operating System :: OS Independent
Classifier: Topic :: Multimedia :: Graphics
Classifier: Topic :: Software Development :: Libraries
Requires-Python: >=3.6
License-File: LICENSE
Requires-Dist: numpy>=1.21.0
Dynamic: author
Dynamic: author-email
Dynamic: classifier
Dynamic: description
Dynamic: description-content-type
Dynamic: home-page
Dynamic: requires-dist
Dynamic: requires-python
Dynamic: summary
